pysyncthru/__init__.py
pysyncthru/tests/__init__.py
pysyncthru/tests/test_web.py
pysyncthru/tests/test_structure/__init__.py
pysyncthru/tests/test_structure/server_control.py
pysyncthru/tests/test_structure/syncthru_mock_server.py
pysyncthru/tests/test_structure/sws/app/information/home/home.json
pysyncthru/tests/web_raw/__init__.py
pysyncthru/tests/web_raw/web_state.py
PySyncThru-0.4.1.dist-info/LICENSE
PySyncThru-0.4.1.dist-info/METADATA
PySyncThru-0.4.1.dist-info/WHEEL
PySyncThru-0.4.1.dist-info/top_level.txt
PySyncThru-0.4.1.dist-info/RECORD
