Metadata-Version: 2.1
Name: PySyncThru
Version: 0.4.1
Summary: Automated JSON API based communication with Samsung SyncThru Web Service
Home-page: https://github.com/nielstron/pysyncthru/
Author: nielstron
Author-email: n.muendler@web.de
License: MIT
Keywords: python syncthru json api samsung printer
Platform: UNKNOWN
Classifier: Development Status :: 3 - Alpha
Classifier: Intended Audience :: Developers
Classifier: Topic :: Software Development :: Object Brokering
Classifier: License :: OSI Approved :: MIT License
Classifier: Programming Language :: Python :: 3.5
Classifier: Programming Language :: Python :: 3.6
Classifier: Programming Language :: Python :: 3.7
Requires-Python: >=3
Requires-Dist: demjson
Requires-Dist: aiohttp
Requires-Dist: async-timeout
